main.py
setup.py
emuMonitor.egg-info/PKG-INFO
emuMonitor.egg-info/SOURCES.txt
emuMonitor.egg-info/dependency_links.txt
emuMonitor.egg-info/requires.txt
emuMonitor.egg-info/top_level.txt